{
  "id": "2026-04-29-wednesday-push",
  "date": "2026-04-29",
  "day_of_week": "wednesday",
  "type": "push",
  "muscle_groups": [
    "chest",
    "triceps",
    "core",
    "abs"
  ],
  "phase": "1 (Observation)",
  "location": "Puerto Escondido — PT gym",
  "trainer": "PXM personal trainer",
  "training_partner": "Jacob",
  "thermocycling": false,
  "fasted": true,
  "warmup_exercises": [],
  "exercises": [],
  "session_notes": "Fasted training (6am, eating window starts at noon).\n**Chest progression — both presses cleaned and bumped:** Incline DB 12 → 14 kg with 15/15/15 across (vs 4/22's 15/15/20 — the long set 3 last week predicted the load bump was earned). Flat DB 16 → 18 kg with 15/15/15 across (vs 4/22's 15/14/14 — rep consistency reclaimed at the higher load). Per [[project_pt_programming_style|PT programming style]], heavy compounds front-loaded and the numbers are landing clean.\n**Triceps held flat:** Rope pushdown at 20 kg × 15 × 3 for the 3rd session in a row. Overhead extension at 29 kg × 15 × 3 for the 2nd session. Both ready for a load bump next push — Jacob matching on both says the loads are well-chosen but not stretching.\n**Core held flat at 4/22 baseline:** V-up hybrid 15 × 2, plank 60s × 2. Light volume; could absorb a third set or add weighted variants.\n**Shoulder gap — parked until Phase 2.** Four straight upper-body sessions with zero direct shoulder/rear-delt work (push 4/22, 4/29; pull 4/21, 4/28). Decision: not raising with PT — two sessions left, not worth the friction. Phase 2 programming (starting May 11) will rebuild direct shoulder volume from session one: press + lateral raise on push days, face pulls / rear delts on pull days.\nJacob still climbing on chest: 6 kg gap on incline (8 vs 14), 6 kg gap on flat (12 vs 18). Triceps and core fully matched.",
  "source_md": "Workout Log/2026-04-29-Wednesday-Push.md"
}
