{
  "format_note": "Append-only inbox written by the web app. Daily scheduled task drains entries[] into vault MD files at Workout Log/YYYY-MM-DD-day-type.md and into data/logs/*.json, then resets to []. Schema: {type: 'log', submitted_at: ISO8601, session: {…full log object…}}",
  "entries": [
    {
      "type": "log",
      "submitted_at": "2026-05-18T13:18:03.440Z",
      "session": {
        "date": "2026-05-18",
        "submitted_at": "2026-05-18T13:18:03.440Z",
        "day_of_week": "monday",
        "type": "push",
        "muscle_groups": [
          "chest",
          "shoulders",
          "lateral-delts",
          "triceps"
        ],
        "routine_id": "2026-W21-Phase-2-Week-2-Progression",
        "phase": "2",
        "exercises": [
          {
            "exercise_id": "flat-db-bench-press",
            "display_name": "Flat Dumbbell Bench Press",
            "sets": [
              {
                "set": 1,
                "weight_kg": 16,
                "reps": 15
              },
              {
                "set": 2,
                "weight_kg": 16,
                "reps": 15
              },
              {
                "set": 3,
                "weight_kg": 16,
                "reps": 15
              }
            ],
            "notes": ""
          },
          {
            "exercise_id": "incline-db-bench-press",
            "display_name": "Incline Dumbbell Bench Press",
            "sets": [
              {
                "set": 1,
                "weight_kg": 16,
                "reps": 15
              },
              {
                "set": 2,
                "weight_kg": 16,
                "reps": 15
              },
              {
                "set": 3,
                "weight_kg": 16,
                "reps": 15
              }
            ],
            "notes": ""
          },
          {
            "exercise_id": "cable-chest-fly",
            "display_name": "Cable Chest Fly",
            "sets": [
              {
                "set": 1,
                "weight_kg": 7,
                "reps": 12
              },
              {
                "set": 2,
                "weight_kg": 7,
                "reps": 15
              },
              {
                "set": 3,
                "weight_kg": 7,
                "reps": 12
              }
            ],
            "notes": ""
          },
          {
            "exercise_id": "seated-db-shoulder-press",
            "display_name": "Seated Dumbbell Shoulder Press",
            "sets": [
              {
                "set": 1,
                "weight_kg": 13.61,
                "reps": 12
              },
              {
                "set": 2,
                "weight_kg": 13.61,
                "reps": 10
              },
              {
                "set": 3,
                "weight_kg": 13.61,
                "reps": 10
              }
            ],
            "notes": ""
          },
          {
            "exercise_id": "db-lateral-raise",
            "display_name": "Dumbbell Lateral Raise",
            "sets": [
              {
                "set": 1,
                "weight_kg": 4.5,
                "reps": 15
              },
              {
                "set": 2,
                "weight_kg": 4.5,
                "reps": 15
              },
              {
                "set": 3,
                "weight_kg": 4.5,
                "reps": 15
              }
            ],
            "notes": ""
          },
          {
            "exercise_id": "rope-tricep-pushdown",
            "display_name": "Rope Tricep Pushdown (Cable)",
            "sets": [
              {
                "set": 1,
                "weight_kg": 9,
                "reps": 15
              },
              {
                "set": 2,
                "weight_kg": 11.34,
                "reps": 15
              },
              {
                "set": 3,
                "weight_kg": 13.61,
                "reps": 15
              }
            ],
            "notes": ""
          }
        ],
        "cooldown": {
          "type": "library",
          "source_key": "push",
          "fitnessplus_name": "",
          "completed_at": "2026-05-18T13:17:55.803Z"
        },
        "session_notes": ""
      }
    },
    {
      "type": "recovery",
      "submitted_at": "2026-05-18T13:18:28.137Z",
      "session": {
        "date": "2026-05-18",
        "location": "Embrace North",
        "rounds": 3,
        "sauna_min": 13,
        "plunge_min": 2,
        "total_min": 44,
        "rounds_detail": [
          {
            "round": 1,
            "sauna_min": 15,
            "plunge_min": 3
          },
          {
            "round": 2,
            "sauna_min": 15,
            "plunge_min": 3
          },
          {
            "round": 3,
            "sauna_min": 8,
            "plunge_min": 0
          }
        ],
        "notes": "",
        "submitted_at": "2026-05-18T13:18:28.137Z"
      }
    }
  ]
}
